string_grouper/__init__.py
string_grouper/string_grouper.py
string_grouper_utils/__init__.py
string_grouper_utils/string_grouper_utils.py
cgvdiit_string_grouper-0.6.1.dist-info/LICENSE
cgvdiit_string_grouper-0.6.1.dist-info/METADATA
cgvdiit_string_grouper-0.6.1.dist-info/WHEEL
cgvdiit_string_grouper-0.6.1.dist-info/top_level.txt
cgvdiit_string_grouper-0.6.1.dist-info/RECORD
