Metadata-Version: 2.1
Name: cgvdiit-string-grouper
Version: 0.6.1
Summary: String grouper contains functions to do string matching using TF-IDF and the cossine similarity. Based on https://bergvca.github.io/2017/10/14/super-fast-string-matching.html
Home-page: https://github.com/Bergvca/string_grouper
Author: Chris van den Berg
Author-email: fake_email@gmail.com
License: MIT License
Platform: UNKNOWN
Requires-Python: >3.7
Requires-Dist: pandas (>=0.25.3)
Requires-Dist: scipy
Requires-Dist: scikit-learn
Requires-Dist: numpy
Requires-Dist: sparse-dot-topn
Requires-Dist: topn (>=0.0.7)
